seaeq/__init__.py
seaeq-0.0.1.dist-info/LICENSE
seaeq-0.0.1.dist-info/METADATA
seaeq-0.0.1.dist-info/WHEEL
seaeq-0.0.1.dist-info/top_level.txt
seaeq-0.0.1.dist-info/RECORD
